Verilog/timer_counter.sv
module timer_counter (
	input logic clk,
	input logic ex_set,
	input logic ex_start,
	input logic [4:0] ex_init,
	output wire ex_done 
);

	logic [4:0] internal_count;

	always @(posedge clk)
		if (ex_set)
			internal_count = ex_init; //load internal_count with new values, add one because the way it counts
		else if (ex_start && (internal_count > 0))
			internal_count = internal_count - 1;

		assign ex_done = (internal_count == 5'b0) ? 1 : 0;

endmodule

Verilog/CTRL_ex_time.sv
module CTRL_ex_time(
  input logic clk,
  input logic reset,
  input logic ex_increase,
  input logic  ex_decrease,
  output logic [4:0] ex_init
);

  always @(posedge clk)
    if (reset)
      ex_init <= 5'd16; // If reset, set it to the middle of range [2,30]
    else if (ex_increase && !ex_decrease && ex_init < 5'd30)
      ex_init <= ex_init + 1; // Increase if ex_increase and ex_init < 30
    else if (ex_decrease && !ex_increase && ex_init > 5'd2)
      ex_init <= ex_init - 1; // Decrease if ex_decrease and ex_init > 2

  // Initial value for ex_init
  initial begin
    ex_init <= 5'd16;
  end

endmodule

Verilog/FSM_ex_control.sv
module FSM_ex_control(
  input logic clk,
  input logic reset,
  input logic init,

  input logic	ex_done,
  output logic ex_start,
  output logic ex_set,

  output logic nre1,
  output logic nre2,
  output logic adc,
  output logic expose,
  output logic erase
);

  enum logic [1:0] {IDLE, EXPOSURE, READOUT, ILLEGAL} current_state;

  logic [3:0] read_state = 0;

  always @(posedge clk) begin

    if (init && current_state == IDLE)begin
      current_state = EXPOSURE;
    end

    if (reset)
      current_state = ILLEGAL;
    
    case (current_state)
      IDLE: begin
        {ex_start, ex_set} = 2'b01;
        {nre1, nre2, adc, expose, erase} = 5'b11001;
      end
      EXPOSURE: begin
        {ex_start, ex_set} = 2'b10;
        {nre1, nre2, adc, expose, erase} = 5'b11010;
        read_state = 0;
      end
      READOUT: begin
        if (reset) begin
          current_state = IDLE;
          {nre1, nre2, adc, expose, erase} = 5'b11001;
        end
          
        
        {expose, erase} = 2'b00;
        case (read_state)
          0: {nre1, nre2, adc} = 3'b110;
          1: {nre1, nre2, adc} = 3'b010;
          2: {nre1, nre2, adc} = 3'b011;
          3: {nre1, nre2, adc} = 3'b010;
          4: {nre1, nre2, adc} = 3'b110;
          5: {nre1, nre2, adc} = 3'b100;
          6: {nre1, nre2, adc} = 3'b101;
          7: {nre1, nre2, adc} = 3'b100;
          8: begin
            {nre1, nre2, adc} = 3'b110; 
            current_state = IDLE;
          end
          default: {nre1, nre2, adc} = 3'b110;
        endcase

        read_state++;
      end
      ILLEGAL: begin
        current_state = IDLE;
        {ex_start, ex_set} = 2'b01;
        {nre1, nre2, adc, expose, erase} = 5'b11001;
      end
    endcase
  end 


  always @(posedge ex_done)
    if (current_state == EXPOSURE) begin
      ex_start = 0;
      current_state = READOUT;
    end

  initial begin
    current_state = IDLE;
    {ex_start, ex_set} = 2'b01;
    {nre1, nre2, adc, expose, erase} = 5'b11001;
  end

endmodule

module FSM_ex_control_tb();

  logic clk, reset, init;
  logic	ex_done;
  wire ex_start, ex_set;

  wire nre1, nre2, adc, expose, erase;

  FSM_ex_control testbench(clk, reset, init, ex_done, ex_start, ex_set, nre1, nre2, adc, expose, erase);


  always begin
    #1 clk = !clk;
  end

  initial begin
    $dumpfile("outfiles/FSM_ex_control/FSM_ex_control_tb.vcd");
    $dumpvars(0, testbench);

    {clk, reset, init, ex_done} = 4'b1000;

    #2 reset = 1;
    #2 reset = 0;

    #2 init = 1;
    #2 init = 0;

    // Simulate exposure time, set it to exposure time * 2 - 2
    #8 ex_done = 1;
    #2 ex_done = 0;

    #20 // Time of readout
    #2 $finish;


  end


endmodule

Verilog/re_control.sv
//
//
// Top-level verilog module example
//

`include "CTRL_ex_time.sv"
`include "FSM_ex_control.sv"
`include "timer_counter.sv"

module re_control(
	input wire clk,
	input wire reset,
	input wire init,

	input wire ex_increase,
	input wire ex_decrease, 

	output wire nre1,
  output wire nre2,
  output wire adc,
  output wire expose,
  output wire erase
);

	wire ex_done;
	wire ex_start;
	wire ex_set;

	wire [4:0] ex_init;


	FSM_ex_control fsm_ex_control(clk, reset, init, ex_done, ex_start, ex_set, nre1, nre2, adc, expose, erase);
	CTRL_ex_time ctrl_ex_time (clk, reset, ex_increase, ex_decrease, ex_init);
	timer_counter ex_timer(clk, ex_set, ex_start, ex_init, ex_done);
	
endmodule // re_control

Verilog/re_control_tb.sv
`include "re_control.sv"

module re_control_tb();
	logic clk;
	logic reset;
	logic init;

	logic ex_increase;
	logic ex_decrease; 

	wire nre1;
  wire nre2;
  wire adc;
  wire expose;
  wire erase;

	re_control testbench(clk, reset, init, ex_increase, ex_decrease, nre1, nre2, adc, expose, erase);

	always begin
		#1 clk = !clk;
	end

	initial begin
		$dumpfile("outfiles/re_control/re_control_tb.vcd");
		$dumpvars(0, testbench);

		{clk, reset, init, ex_increase, ex_decrease} = 5'b10000;

		#2 reset = 1;
		#2 reset = 0;

		#2 ex_decrease = 1;
		#12 ex_decrease = 0;

		#2 init = 1;
		#2 init = 0;

		#46 $finish; 
	end


endmodule

Verilog/outfiles/re_control/re_control_tb.vcd
$date
	Tue Nov 17 11:34:40 2020
$end
$version
	Icarus Verilog
$end
$timescale
	1s
$end
$scope module re_control_tb $end
$scope module testbench $end
$var wire 1 ! clk $end
$var wire 1 " ex_decrease $end
$var wire 1 # ex_increase $end
$var wire 1 $ init $end
$var wire 1 % reset $end
$var wire 1 & nre2 $end
$var wire 1 ' nre1 $end
$var wire 1 ( expose $end
$var wire 1 ) ex_start $end
$var wire 1 * ex_set $end
$var wire 5 + ex_init [4:0] $end
$var wire 1 , ex_done $end
$var wire 1 - erase $end
$var wire 1 . adc $end
$scope module ctrl_ex_time $end
$var wire 1 ! clk $end
$var wire 1 " ex_decrease $end
$var wire 1 # ex_increase $end
$var wire 1 % reset $end
$var reg 5 / ex_init [4:0] $end
$upscope $end
$scope module ex_timer $end
$var wire 1 ! clk $end
$var wire 5 0 ex_init [4:0] $end
$var wire 1 ) ex_start $end
$var wire 1 * ex_set $end
$var wire 1 , ex_done $end
$var reg 5 1 internal_count [4:0] $end
$upscope $end
$scope module fsm_ex_control $end
$var wire 1 ! clk $end
$var wire 1 , ex_done $end
$var wire 1 $ init $end
$var wire 1 % reset $end
$var reg 1 . adc $end
$var reg 2 2 current_state [1:0] $end
$var reg 1 - erase $end
$var reg 1 * ex_set $end
$var reg 1 ) ex_start $end
$var reg 1 ( expose $end
$var reg 1 ' nre1 $end
$var reg 1 & nre2 $end
$var reg 4 3 read_state [3:0] $end
$upscope $end
$upscope $end
$upscope $end
$enddefinitions $end
#0
$dumpvars
b0 3
b0 2
bx 1
b10000 0
b10000 /
0.
1-
x,
b10000 +
1*
0)
0(
1'
1&
0%
0$
0#
0"
1!
$end
#1
0!
#2
0,
b10000 1
b0 2
1!
1%
#3
0!
#4
1!
0%
#5
0!
#6
b1111 +
b1111 /
b1111 0
1!
1"
#7
0!
#8
b1110 +
b1110 /
b1110 0
b1111 1
1!
#9
0!
#10
b1101 +
b1101 /
b1101 0
b1110 1
1!
#11
0!
#12
b1100 +
b1100 /
b1100 0
b1101 1
1!
#13
0!
#14
b1011 +
b1011 /
b1011 0
b1100 1
1!
#15
0!
#16
b1010 +
b1010 /
b1010 0
b1011 1
1!
#17
0!
#18
b1010 1
1!
0"
#19
0!
#20
1(
0-
1)
0*
b1 2
1!
1$
#21
0!
#22
b1001 1
1!
0$
#23
0!
#24
b1000 1
1!
#25
0!
#26
b111 1
1!
#27
0!
#28
b110 1
1!
#29
0!
#30
b101 1
1!
#31
0!
#32
b100 1
1!
#33
0!
#34
b11 1
1!
#35
0!
#36
b10 1
1!
#37
0!
#38
b1 1
1!
#39
0!
#40
b10 2
0(
0)
1,
b0 1
1!
#41
0!
#42
b1 3
1!
#43
0!
#44
b10 3
0'
1!
#45
0!
#46
b11 3
1.
1!
#47
0!
#48
b100 3
0.
1!
#49
0!
#50
b101 3
1'
1!
#51
0!
#52
b110 3
0&
1!
#53
0!
#54
b111 3
1.
1!
#55
0!
#56
b1000 3
0.
1!
#57
0!
#58
b1001 3
b0 2
1&
1!
#59
0!
#60
1-
1*
1!
#61
0!
#62
0,
b1010 1
1!
