Verilog/CTRL_ex_time.sv
module CTRL_ex_time(
	input 	logic 				clk,
	input 	logic 				reset,
	input 	logic 				ex_increase,
	input 	logic 				ex_decrease,
	output 	logic [4:0] 	init
);

	always @(posedge clk)
		if (reset)
			init <= 5'd16; // If reset, set it to the middle of range [2,30]
		else if (ex_increase && !ex_decrease && init < 5'd30)
			init <= init + 1; // Increase if ex_increase and init < 30
		else if (ex_decrease && !ex_increase && init > 5'd2)
			init <= init - 1; // Decrease if ex_decrease and init > 2

	initial begin
		init <= 5'd16;
	end

endmodule


module CTRL_ex_time_tb();
	
	logic clk, reset, ex_increase, ex_decrease;
	wire [4:0] init;

	CTRL_ex_time testbench(clk, reset, ex_increase, ex_decrease, init);

	always begin
		#1 clk = !clk;
	end

	initial begin
		$dumpfile("outfiles/CTRL_ex_time/CTRL_ex_time_tb.vcd");
		$dumpvars();

		{clk, reset, ex_increase, ex_decrease} = 4'b1000; // Start with clock on

		// Test counting;
		#4 ex_increase = 1;
		#10 ex_increase = 0;
		#4 ex_decrease = 1;
		#20 ex_decrease = 0;

		// Test if both buttons is high
		#4 {ex_increase, ex_decrease} = 2'b11;
		#4 {ex_increase, ex_decrease} = 2'b00;

		// Test reset
		#2 reset = 1;
		#2 reset = 0;

		// Test of the upper limit
		#2 ex_increase = 1;
		#30 ex_increase = 0; 

		// Reset before testing lower limit
		#2 reset = 1;
		#2 reset = 0;

		// Test of the lower limit
		#2 ex_decrease = 1;
		#30 ex_decrease = 0; 

		// Check if all is high
		#4 {reset, ex_increase, ex_decrease} = 3'b111;
		#4 {reset, ex_increase, ex_decrease} = 3'b000;
		#2 $finish;
	end


endmodule

Verilog/outfiles/CTRL_ex_time/CTRL_ex_time_tb.vcd
$date
	Mon Nov 16 16:08:04 2020
$end
$version
	Icarus Verilog
$end
$timescale
	1s
$end
$scope module CTRL_ex_time_tb $end
$scope module testbench $end
$var wire 1 ! clk $end
$var wire 1 " ex_decrease $end
$var wire 1 # ex_increase $end
$var wire 1 $ reset $end
$var reg 5 % init [4:0] $end
$upscope $end
$upscope $end
$enddefinitions $end
#0
$dumpvars
b10000 %
0$
0#
0"
1!
$end
#1
0!
#2
1!
#3
0!
#4
b10001 %
1!
1#
#5
0!
#6
b10010 %
1!
#7
0!
#8
b10011 %
1!
#9
0!
#10
b10100 %
1!
#11
0!
#12
b10101 %
1!
#13
0!
#14
1!
0#
#15
0!
#16
1!
#17
0!
#18
b10100 %
1!
1"
#19
0!
#20
b10011 %
1!
#21
0!
#22
b10010 %
1!
#23
0!
#24
b10001 %
1!
#25
0!
#26
b10000 %
1!
#27
0!
#28
b1111 %
1!
#29
0!
#30
b1110 %
1!
#31
0!
#32
b1101 %
1!
#33
0!
#34
b1100 %
1!
#35
0!
#36
b1011 %
1!
#37
0!
#38
1!
0"
#39
0!
#40
1!
#41
0!
#42
1!
1#
1"
#43
0!
#44
1!
#45
0!
#46
1!
0#
0"
#47
0!
#48
b10000 %
1!
1$
#49
0!
#50
1!
0$
#51
0!
#52
b10001 %
1!
1#
#53
0!
#54
b10010 %
1!
#55
0!
#56
b10011 %
1!
#57
0!
#58
b10100 %
1!
#59
0!
#60
b10101 %
1!
#61
0!
#62
b10110 %
1!
#63
0!
#64
b10111 %
1!
#65
0!
#66
b11000 %
1!
#67
0!
#68
b11001 %
1!
#69
0!
#70
b11010 %
1!
#71
0!
#72
b11011 %
1!
#73
0!
#74
b11100 %
1!
#75
0!
#76
b11101 %
1!
#77
0!
#78
b11110 %
1!
#79
0!
#80
1!
#81
0!
#82
1!
0#
#83
0!
#84
b10000 %
1!
1$
#85
0!
#86
1!
0$
#87
0!
#88
b1111 %
1!
1"
#89
0!
#90
b1110 %
1!
#91
0!
#92
b1101 %
1!
#93
0!
#94
b1100 %
1!
#95
0!
#96
b1011 %
1!
#97
0!
#98
b1010 %
1!
#99
0!
#100
b1001 %
1!
#101
0!
#102
b1000 %
1!
#103
0!
#104
b111 %
1!
#105
0!
#106
b110 %
1!
#107
0!
#108
b101 %
1!
#109
0!
#110
b100 %
1!
#111
0!
#112
b11 %
1!
#113
0!
#114
b10 %
1!
#115
0!
#116
1!
#117
0!
#118
1!
0"
#119
0!
#120
1!
#121
0!
#122
b10000 %
1!
1$
1#
1"
#123
0!
#124
1!
#125
0!
#126
1!
0$
0#
0"
