Verilog/FSM_ex_control.sv
module FSM_ex_control(
  input logic clk,
  input logic reset,
  input logic init,

  input logic	ex_done,
  output logic ex_start,
  output logic ex_set,

  output logic nre1,
  output logic nre2,
  output logic adc,
  output logic expose,
  output logic erase
);

  enum logic [1:0] {IDLE, EXPOSURE, READOUT, ILLEGAL} current_state;

  logic [3:0] read_state = 0;

  always @(posedge clk) begin

    if (init && current_state == IDLE)begin
      current_state = EXPOSURE;
    end

    if (reset)
      current_state = ILLEGAL;
    
    case (current_state)
      IDLE: begin
        {ex_start, ex_set} = 2'b01;
        {nre1, nre2, adc, expose, erase} = 5'b11001;
      end
      EXPOSURE: begin
        {ex_start, ex_set} = 2'b10;
        {nre1, nre2, adc, expose, erase} = 5'b11010;
        read_state = 0;
      end
      READOUT: begin
        if (reset) begin
          current_state = IDLE;
          {nre1, nre2, adc, expose, erase} = 5'b11001;
        end
          
        
        {expose, erase} = 2'b00;
        case (read_state)
          0: {nre1, nre2, adc} = 3'b110;
          1: {nre1, nre2, adc} = 3'b010;
          2: {nre1, nre2, adc} = 3'b011;
          3: {nre1, nre2, adc} = 3'b010;
          4: {nre1, nre2, adc} = 3'b110;
          5: {nre1, nre2, adc} = 3'b100;
          6: {nre1, nre2, adc} = 3'b101;
          7: {nre1, nre2, adc} = 3'b100;
          8: begin
            {nre1, nre2, adc} = 3'b110; 
            current_state = IDLE;
          end
          default: {nre1, nre2, adc} = 3'b110;
        endcase

        read_state++;
      end
      ILLEGAL: begin
        current_state = IDLE;
        {ex_start, ex_set} = 2'b01;
        {nre1, nre2, adc, expose, erase} = 5'b11001;
      end
    endcase
  end 


  always @(posedge ex_done)
    if (current_state == EXPOSURE) begin
      ex_start = 0;
      current_state = READOUT;
    end

  initial begin
    current_state = IDLE;
    {ex_start, ex_set} = 2'b01;
    {nre1, nre2, adc, expose, erase} = 5'b11001;
  end

endmodule

module FSM_ex_control_tb();

  logic clk, reset, init;
  logic	ex_done;
  wire ex_start, ex_set;

  wire nre1, nre2, adc, expose, erase;

  FSM_ex_control testbench(clk, reset, init, ex_done, ex_start, ex_set, nre1, nre2, adc, expose, erase);


  always begin
    #1 clk = !clk;
  end

  initial begin
    $dumpfile("outfiles/FSM_ex_control/FSM_ex_control_tb.vcd");
    $dumpvars(0, testbench);

    {clk, reset, init, ex_done} = 4'b1000;

    #2 reset = 1;
    #2 reset = 0;

    #2 init = 1;
    #2 init = 0;

    // Simulate exposure time, set it to exposure time * 2 - 2
    #8 ex_done = 1;
    #2 ex_done = 0;

    #20 // Time of readout
    #2 $finish;


  end


endmodule

Verilog/outfiles/FSM_ex_control/FSM_ex_control_tb.vcd
$date
	Mon Nov 16 14:56:14 2020
$end
$version
	Icarus Verilog
$end
$timescale
	1s
$end
$scope module FSM_ex_control_tb $end
$scope module testbench $end
$var wire 1 ! clk $end
$var wire 1 " ex_done $end
$var wire 1 # init $end
$var wire 1 $ reset $end
$var reg 1 % adc $end
$var reg 2 & current_state [1:0] $end
$var reg 1 ' erase $end
$var reg 1 ( ex_set $end
$var reg 1 ) ex_start $end
$var reg 1 * expose $end
$var reg 1 + nre1 $end
$var reg 1 , nre2 $end
$var reg 4 - read_state [3:0] $end
$upscope $end
$upscope $end
$enddefinitions $end
#0
$dumpvars
b0 -
1,
1+
0*
0)
1(
1'
b0 &
0%
0$
0#
0"
1!
$end
#1
0!
#2
b0 &
1!
1$
#3
0!
#4
1!
0$
#5
0!
#6
1*
0'
1)
0(
b1 &
1!
1#
#7
0!
#8
1!
0#
#9
0!
#10
1!
#11
0!
#12
1!
#13
0!
#14
1!
#15
0!
#16
b1 -
0*
b10 &
0)
1!
1"
#17
0!
#18
b10 -
0+
1!
0"
#19
0!
#20
b11 -
1%
1!
#21
0!
#22
b100 -
0%
1!
#23
0!
#24
b101 -
1+
1!
#25
0!
#26
b110 -
0,
1!
#27
0!
#28
b111 -
1%
1!
#29
0!
#30
b1000 -
0%
1!
#31
0!
#32
b1001 -
b0 &
1,
1!
#33
0!
#34
1'
1(
1!
