Verilog/timer_counter.sv
module timer_counter (input logic clk,
                      input logic reset,
                      input logic enable,
                      input logic [4:0] init,
                      output wire exposure_done );
	logic [4:0] internal_count;

	always @(posedge clk)
		if (reset)
			internal_count = init + 1; //load internal_count with new values, add one because the way it counts
		else if (enable && (internal_count > 0))
			internal_count = internal_count-1;

		assign exposure_done = (internal_count == 5'b0) ? 1 : 0;
endmodule



module timer_counter_tb();

	logic clk, reset, enable;
	wire exposure_done;
	logic [4:0] init;

	timer_counter testbench(clk, reset, enable, init, exposure_done);


	always begin
		#1 clk = !clk;
	end

	initial
	begin
		$dumpfile("outfiles/timer_counter_tb.vcd");
		$dumpvars();

		{clk, enable, reset} = 3'b100;
		init = 5'd10;
		#2 {enable, reset} = 2'b01;
		#2 {enable, reset} = 2'b10;
	end

	always @(posedge exposure_done)
	begin
		#2 {enable, reset} = 2'b00;
		#4 {enable, reset} = 2'b01;
		#4 $finish;
	end
endmodule

Verilog/outfiles/timer_counter_tb.vcd
$date
	Sat Nov 14 16:31:36 2020
$end
$version
	Icarus Verilog
$end
$timescale
	1s
$end
$scope module timer_counter_tb $end
$var wire 1 ! exposure_done $end
$var reg 1 " clk $end
$var reg 1 # enable $end
$var reg 5 $ init [4:0] $end
$var reg 1 % reset $end
$scope module testbench $end
$var wire 1 " clk $end
$var wire 1 # enable $end
$var wire 5 & init [4:0] $end
$var wire 1 % reset $end
$var wire 1 ! exposure_done $end
$var reg 5 ' internal_count [4:0] $end
$upscope $end
$upscope $end
$enddefinitions $end
#0
$dumpvars
bx '
b1010 &
0%
b1010 $
0#
1"
x!
$end
#1
0"
#2
0!
b1011 '
1"
1%
#3
0"
#4
b1010 '
1"
1#
0%
#5
0"
#6
b1001 '
1"
#7
0"
#8
b1000 '
1"
#9
0"
#10
b111 '
1"
#11
0"
#12
b110 '
1"
#13
0"
#14
b101 '
1"
#15
0"
#16
b100 '
1"
#17
0"
#18
b11 '
1"
#19
0"
#20
b10 '
1"
#21
0"
#22
b1 '
1"
#23
0"
#24
1!
b0 '
1"
#25
0"
#26
1"
0#
#27
0"
#28
1"
#29
0"
#30
0!
b1011 '
1"
1%
