Verilog/timer_counter.sv
module timer_counter (
	input logic clk,
	input logic ex_set,
	input logic ex_start,
	input logic [4:0] ex_init,
	output wire ex_done 
);

	logic [4:0] internal_count;

	always @(posedge clk)
		if (ex_set)
			internal_count = ex_init; //load internal_count with new values, add one because the way it counts
		else if (ex_start && (internal_count > 0))
			internal_count = internal_count - 1;

		assign ex_done = (internal_count == 5'b0) ? 1 : 0;

endmodule

Verilog/timer_counter_tb.sv
`include "timer_counter.sv"

module timer_counter_tb();

  logic clk, ex_set, ex_start;
  wire ex_done;
  logic [4:0] ex_init;

  timer_counter testbench(clk, ex_set, ex_start, ex_init, ex_done);

  // Clock
  always begin
    #1 clk = !clk;
  end

  initial begin
    $dumpfile("outfiles/timer_counter/timer_counter_tb.vcd");
    $dumpvars(0, testbench);

    // Start with clock high 
    {clk, ex_start, ex_set} = 3'b100;
    // Set start value for counter, usually controlled by CTRL_ex_time
    // Here we count down from decimal 10
    ex_init = 5'd10;
    // Pulse ex_set to set value to count down from
    #2 {ex_start, ex_set} = 2'b01;
    #2 {ex_start, ex_set} = 2'b10;
  end

  // When the ex_done is set high, stop the simulation
  always @(posedge ex_done) begin
    #2 {ex_start, ex_set} = 2'b00;
    #4 {ex_start, ex_set} = 2'b01;
    #4 $finish;
  end
endmodule

Verilog/outfiles/timer_counter/timer_counter_tb.vcd
$date
	Tue Nov 17 13:21:49 2020
$end
$version
	Icarus Verilog
$end
$timescale
	1s
$end
$scope module timer_counter_tb $end
$scope module testbench $end
$var wire 1 ! clk $end
$var wire 5 " ex_init [4:0] $end
$var wire 1 # ex_set $end
$var wire 1 $ ex_start $end
$var wire 1 % ex_done $end
$var reg 5 & internal_count [4:0] $end
$upscope $end
$upscope $end
$enddefinitions $end
#0
$dumpvars
bx &
x%
0$
0#
b1010 "
1!
$end
#1
0!
#2
0%
b1010 &
1!
1#
#3
0!
#4
b1001 &
1!
1$
0#
#5
0!
#6
b1000 &
1!
#7
0!
#8
b111 &
1!
#9
0!
#10
b110 &
1!
#11
0!
#12
b101 &
1!
#13
0!
#14
b100 &
1!
#15
0!
#16
b11 &
1!
#17
0!
#18
b10 &
1!
#19
0!
#20
b1 &
1!
#21
0!
#22
1%
b0 &
1!
#23
0!
#24
1!
0$
#25
0!
#26
1!
#27
0!
#28
0%
b1010 &
1!
1#
